{
  "animations": [
    {
      "id": 1,
      "title": "200 Iq Math Calculations Meme",
      "credit": "",
      "filetype": "mp4"
    },
    {
      "id": 2,
      "title": "Abstract Lines Background",
      "credit": "",
      "filetype": "mp4"
    },
    {
      "id": 3,
      "title": "All Nether Mobs",
      "credit": "",
      "filetype": "mp4"
    },
    {
      "id": 4,
      "title": "Anime White Speed Lines",
      "credit": "",
      "filetype": "mp4"
    },
    {
      "id": 5,
      "title": "Arrow Bowshot Og",
      "credit": "",
      "filetype": "mp4"
    },
    {
      "id": 6,
      "title": "Blank Pages Book",
      "credit": "",
      "filetype": "mov"
    },
    {
      "id": 7,
      "title": "Calendar Day Counter Spinning",
      "credit": "nothingbruv",
      "filetype": "mp4"
    },
    {
      "id": 8,
      "title": "Chain Locked",
      "credit": "",
      "filetype": "mp4"
    },
    {
      "id": 9,
      "title": "Chest Open Closed",
      "credit": "",
      "filetype": "mp4"
    },
    {
      "id": 10,
      "title": "Chest Totem Of Undying",
      "credit": "",
      "filetype": "mp4"
    },
    {
      "id": 11,
      "title": "Clock Ticking Time",
      "credit": "",
      "filetype": "mp4"
    },
    {
      "id": 12,
      "title": "Craft Boat",
      "credit": "",
      "filetype": "mp4"
    },
    {
      "id": 13,
      "title": "Craft Diamond Armor",
      "credit": "",
      "filetype": "mp4"
    },
    {
      "id": 14,
      "title": "Craft Diamond Pickaxe",
      "credit": "",
      "filetype": "mp4"
    },
    {
      "id": 15,
      "title": "Craft Diamond Sword",
      "credit": "",
      "filetype": "mp4"
    },
    {
      "id": 16,
      "title": "Craft Enchanting Table",
      "credit": "",
      "filetype": "mp4"
    },
    {
      "id": 17,
      "title": "Craft Glowing Rainbow Neon",
      "credit": "",
      "filetype": "mp4"
    },
    {
      "id": 18,
      "title": "Craft Ladder",
      "credit": "",
      "filetype": "mp4"
    },
    {
      "id": 19,
      "title": "Craft Nether Portal",
      "credit": "",
      "filetype": "mp4"
    },
    {
      "id": 20,
      "title": "Day Counter 1-100",
      "credit": "",
      "filetype": "mov"
    },
    {
      "id": 21,
      "title": "Dead Coffin Dance",
      "credit": "",
      "filetype": "mp4"
    },
    {
      "id": 22,
      "title": "Diamond Glint",
      "credit": "",
      "filetype": "webm"
    },
    {
      "id": 23,
      "title": "Diamond Wipe Transition",
      "credit": "",
      "filetype": "mov"
    },
    {
      "id": 24,
      "title": "Difficulty Change Hardcore 1",
      "credit": "",
      "filetype": "mov"
    },
    {
      "id": 25,
      "title": "Difficulty Change Hardcore 2",
      "credit": "",
      "filetype": "mp4"
    },
    {
      "id": 26,
      "title": "Difficulty Change Hardcore 3",
      "credit": "",
      "filetype": "mp4"
    },
    {
      "id": 27,
      "title": "Discord Call",
      "credit": "",
      "filetype": "mp4"
    },
    {
      "id": 28,
      "title": "Discord Join 1",
      "credit": "boombaboo",
      "filetype": "mp4"
    },
    {
      "id": 29,
      "title": "Discord Join 2",
      "credit": "arkify",
      "filetype": "mp4"
    },
    {
      "id": 30,
      "title": "Discord Join 3",
      "credit": "motionbychris",
      "filetype": "mov"
    },
    {
      "id": 31,
      "title": "Discord Join 4",
      "credit": "",
      "filetype": "mov"
    },
    {
      "id": 32,
      "title": "End Crystal Explosion Blast",
      "credit": "",
      "filetype": "mov"
    },
    {
      "id": 33,
      "title": "Five Stars Review",
      "credit": "",
      "filetype": "mov"
    },
    {
      "id": 34,
      "title": "Full Diamond Leather Gold Armor Player Falling",
      "credit": "",
      "filetype": "mov"
    },
    {
      "id": 35,
      "title": "Full Netherite Armor Player Falling",
      "credit": "",
      "filetype": "mp4"
    },
    {
      "id": 36,
      "title": "Grid Lines Rule Of Thirds",
      "credit": "",
      "filetype": "mov"
    },
    {
      "id": 37,
      "title": "Hoplite Logo",
      "credit": "",
      "filetype": "mp4"
    },
    {
      "id": 38,
      "title": "Horizontal Black Bars",
      "credit": "",
      "filetype": "mp4"
    },
    {
      "id": 39,
      "title": "Hunger Bar",
      "credit": "",
      "filetype": "mov"
    },
    {
      "id": 40,
      "title": "Iron Sword Wipe Transition",
      "credit": "",
      "filetype": "mov"
    },
    {
      "id": 41,
      "title": "Join Server",
      "credit": "",
      "filetype": "mov"
    },
    {
      "id": 42,
      "title": "Lines On Ground Trail Background",
      "credit": "",
      "filetype": "mp4"
    },
    {
      "id": 43,
      "title": "Live Streaming",
      "credit": "",
      "filetype": "mp4"
    },
    {
      "id": 44,
      "title": "Loading Bar Error",
      "credit": "",
      "filetype": "mp4"
    },
    {
      "id": 45,
      "title": "Loading Progress Bar 1",
      "credit": "",
      "filetype": "mp4"
    },
    {
      "id": 46,
      "title": "Loading Progress Bar 2",
      "credit": "",
      "filetype": "mov"
    },
    {
      "id": 47,
      "title": "Losing Heart Broken Undertale Dead Kill",
      "credit": "",
      "filetype": "mp4"
    },
    {
      "id": 48,
      "title": "Map 1",
      "credit": "",
      "filetype": "mp4"
    },
    {
      "id": 49,
      "title": "Map 2",
      "credit": "",
      "filetype": "mp4"
    },
    {
      "id": 50,
      "title": "Mcc Island Logo",
      "credit": "",
      "filetype": "mp4"
    },
    {
      "id": 51,
      "title": "Minecraft Map Destination",
      "credit": "",
      "filetype": "mp4"
    },
    {
      "id": 52,
      "title": "Money Rich Usd",
      "credit": "",
      "filetype": "mp4"
    },
    {
      "id": 53,
      "title": "Paper Background",
      "credit": "",
      "filetype": "mp4"
    },
    {
      "id": 54,
      "title": "Play And Pause Video 2",
      "credit": "",
      "filetype": "mp4"
    },
    {
      "id": 55,
      "title": "Play And Pause Video",
      "credit": "",
      "filetype": "mp4"
    },
    {
      "id": 56,
      "title": "Play Pause Video Player 2",
      "credit": "",
      "filetype": "mp4"
    },
    {
      "id": 57,
      "title": "Play Pause Video Player",
      "credit": "",
      "filetype": "mp4"
    },
    {
      "id": 58,
      "title": "Players Joining Server Flood",
      "credit": "",
      "filetype": "mov"
    },
    {
      "id": 59,
      "title": "Progress Loading Bar",
      "credit": "",
      "filetype": "mov"
    },
    {
      "id": 60,
      "title": "Scrolling Through Hotbar",
      "credit": "",
      "filetype": "mp4"
    },
    {
      "id": 61,
      "title": "Selection Screen",
      "credit": "",
      "filetype": "mov"
    },
    {
      "id": 62,
      "title": "Slider",
      "credit": "",
      "filetype": "mp4"
    },
    {
      "id": 63,
      "title": "Smp Apply Button",
      "credit": "jmlgyt",
      "filetype": "mp4"
    },
    {
      "id": 64,
      "title": "Stonks Success Green Line",
      "credit": "",
      "filetype": "mp4"
    },
    {
      "id": 65,
      "title": "Straight Lines Grid Background",
      "credit": "",
      "filetype": "mov"
    },
    {
      "id": 66,
      "title": "Stronghold Map Route",
      "credit": "",
      "filetype": "mp4"
    },
    {
      "id": 67,
      "title": "Subscribe 1",
      "credit": "",
      "filetype": "mov"
    },
    {
      "id": 68,
      "title": "Subscribe 10 Blue",
      "credit": "",
      "filetype": "mp4"
    },
    {
      "id": 69,
      "title": "Subscribe 10 Red",
      "credit": "",
      "filetype": "mp4"
    },
    {
      "id": 70,
      "title": "Subscribe 11",
      "credit": "",
      "filetype": "mp4"
    },
    {
      "id": 71,
      "title": "Subscribe 12",
      "credit": "",
      "filetype": "mp4"
    },
    {
      "id": 72,
      "title": "Subscribe 13",
      "credit": "",
      "filetype": "mp4"
    },
    {
      "id": 73,
      "title": "Subscribe 15",
      "credit": "",
      "filetype": "mp4"
    },
    {
      "id": 74,
      "title": "Subscribe 16",
      "credit": "",
      "filetype": "mp4"
    },
    {
      "id": 75,
      "title": "Subscribe 17",
      "credit": "",
      "filetype": "mov"
    },
    {
      "id": 76,
      "title": "Subscribe 18",
      "credit": "",
      "filetype": "mov"
    },
    {
      "id": 77,
      "title": "Subscribe 2 Going Down",
      "credit": "motionbychris",
      "filetype": "mp4"
    },
    {
      "id": 78,
      "title": "Subscribe 2 Going Up",
      "credit": "motionbychris",
      "filetype": "mp4"
    },
    {
      "id": 79,
      "title": "Subscribe 2",
      "credit": "arialfx",
      "filetype": "mp4"
    },
    {
      "id": 80,
      "title": "Subscribe 3",
      "credit": "boombaboo",
      "filetype": "mp4"
    },
    {
      "id": 81,
      "title": "Subscribe 4",
      "credit": "advanceds",
      "filetype": "mp4"
    },
    {
      "id": 82,
      "title": "Subscribe 5",
      "credit": "advanceds",
      "filetype": "mp4"
    },
    {
      "id": 83,
      "title": "Subscribe 6",
      "credit": "",
      "filetype": "mp4"
    },
    {
      "id": 84,
      "title": "Subscribe 7",
      "credit": "jiggy",
      "filetype": "mov"
    },
    {
      "id": 85,
      "title": "Subscribe 8",
      "credit": "miki neomi",
      "filetype": "mp4"
    },
    {
      "id": 86,
      "title": "Subscribe 9",
      "credit": "arialfx",
      "filetype": "mp4"
    },
    {
      "id": 87,
      "title": "Ten Seconds Countdown Timer Clock",
      "credit": "",
      "filetype": "mov"
    },
    {
      "id": 88,
      "title": "Time Ticking Clock",
      "credit": "",
      "filetype": "mp4"
    },
    {
      "id": 89,
      "title": "Tnt Explosion",
      "credit": "",
      "filetype": "mp4"
    },
    {
      "id": 90,
      "title": "Totem Pop",
      "credit": "liffeykid",
      "filetype": "mp4"
    },
    {
      "id": 91,
      "title": "Twitch Follow Dark",
      "credit": "motionbychris",
      "filetype": "mp4"
    },
    {
      "id": 92,
      "title": "Twitch Follow Light",
      "credit": "motionbychris",
      "filetype": "mp4"
    },
    {
      "id": 93,
      "title": "Virus Error Popups",
      "credit": "",
      "filetype": "mp4"
    },
    {
      "id": 94,
      "title": "Winner Trophy",
      "credit": "",
      "filetype": "mov"
    },
    {
      "id": 95,
      "title": "Youtube Comment 1",
      "credit": "advanceds",
      "filetype": "mp4"
    },
    {
      "id": 96,
      "title": "Youtube Like",
      "credit": "",
      "filetype": "mp4"
    },
    {
      "id": 97,
      "title": "Youtube Shorts Like",
      "credit": "",
      "filetype": "mov"
    }
  ],
  "fonts": [
    {
      "id": 98,
      "title": "Burbank Bold",
      "credit": "",
      "filetype": "ttf"
    },
    {
      "id": 99,
      "title": "Gotham",
      "credit": "",
      "filetype": "ttf"
    },
    {
      "id": 100,
      "title": "Hey Comic",
      "credit": "",
      "filetype": "ttf"
    },
    {
      "id": 101,
      "title": "Kgredhands",
      "credit": "",
      "filetype": "ttf"
    },
    {
      "id": 102,
      "title": "Lemonmilk Bold",
      "credit": "",
      "filetype": "ttf"
    },
    {
      "id": 103,
      "title": "Luckiestguy",
      "credit": "",
      "filetype": "ttf"
    },
    {
      "id": 104,
      "title": "Minecraft Five Bold",
      "credit": "",
      "filetype": "ttf"
    },
    {
      "id": 105,
      "title": "Minecraft",
      "credit": "",
      "filetype": "ttf"
    },
    {
      "id": 106,
      "title": "Minecraftia",
      "credit": "",
      "filetype": "ttf"
    },
    {
      "id": 107,
      "title": "Mont Heavy",
      "credit": "",
      "filetype": "otf"
    },
    {
      "id": 108,
      "title": "Montserrat Bold",
      "credit": "",
      "filetype": "ttf"
    },
    {
      "id": 109,
      "title": "Montserrat Extrabold",
      "credit": "",
      "filetype": "ttf"
    },
    {
      "id": 110,
      "title": "Obelixpro",
      "credit": "",
      "filetype": "ttf"
    },
    {
      "id": 111,
      "title": "Panton Black",
      "credit": "",
      "filetype": "ttf"
    },
    {
      "id": 112,
      "title": "Pixel Square Bold10",
      "credit": "",
      "filetype": "ttf"
    },
    {
      "id": 113,
      "title": "Pixelsix10",
      "credit": "",
      "filetype": "ttf"
    },
    {
      "id": 114,
      "title": "Riffic Bold",
      "credit": "",
      "filetype": "ttf"
    }
  ],
  "images": [
    {
      "id": 115,
      "title": "Arrow 1",
      "credit": "",
      "filetype": "png"
    },
    {
      "id": 116,
      "title": "Arrow 2",
      "credit": "",
      "filetype": "png"
    },
    {
      "id": 117,
      "title": "Arrow 3",
      "credit": "",
      "filetype": "png"
    },
    {
      "id": 118,
      "title": "Arrow 4",
      "credit": "",
      "filetype": "png"
    },
    {
      "id": 119,
      "title": "Arrow 5",
      "credit": "",
      "filetype": "png"
    },
    {
      "id": 120,
      "title": "Arrow 6",
      "credit": "",
      "filetype": "png"
    },
    {
      "id": 121,
      "title": "Blue Button Without Text",
      "credit": "",
      "filetype": "png"
    },
    {
      "id": 122,
      "title": "Calendar",
      "credit": "",
      "filetype": "png"
    },
    {
      "id": 123,
      "title": "Charged Crossbow",
      "credit": "",
      "filetype": "png"
    },
    {
      "id": 124,
      "title": "Clouds",
      "credit": "",
      "filetype": "png"
    },
    {
      "id": 125,
      "title": "Cross",
      "credit": "",
      "filetype": "png"
    },
    {
      "id": 126,
      "title": "Cursor",
      "credit": "",
      "filetype": "png"
    },
    {
      "id": 127,
      "title": "Discord Logo",
      "credit": "",
      "filetype": "png"
    },
    {
      "id": 128,
      "title": "Empty Achievement Gui",
      "credit": "",
      "filetype": "png"
    },
    {
      "id": 129,
      "title": "Empty Enchanting Boxes Gui",
      "credit": "",
      "filetype": "png"
    },
    {
      "id": 130,
      "title": "Empty Lunar Client Mod",
      "credit": "",
      "filetype": "png"
    },
    {
      "id": 131,
      "title": "Experience Orb",
      "credit": "",
      "filetype": "png"
    },
    {
      "id": 132,
      "title": "First Person Charging Holding Bow",
      "credit": "",
      "filetype": "png"
    },
    {
      "id": 133,
      "title": "First Person Hand",
      "credit": "",
      "filetype": "png"
    },
    {
      "id": 134,
      "title": "First Person Holding Diamond Pickaxe",
      "credit": "",
      "filetype": "png"
    },
    {
      "id": 135,
      "title": "First Person Holding Diamond Sword",
      "credit": "",
      "filetype": "png"
    },
    {
      "id": 136,
      "title": "First Person Holding Golden Pickaxe",
      "credit": "",
      "filetype": "png"
    },
    {
      "id": 137,
      "title": "First Person Holding Golden Sword",
      "credit": "",
      "filetype": "png"
    },
    {
      "id": 138,
      "title": "First Person Holding Iron Pickaxe",
      "credit": "",
      "filetype": "png"
    },
    {
      "id": 139,
      "title": "First Person Holding Iron Sword",
      "credit": "",
      "filetype": "png"
    },
    {
      "id": 140,
      "title": "First Person Holding Lava Bucket",
      "credit": "",
      "filetype": "png"
    },
    {
      "id": 141,
      "title": "First Person Holding Netherite Pickaxe",
      "credit": "",
      "filetype": "png"
    },
    {
      "id": 142,
      "title": "First Person Holding Netherite Sword",
      "credit": "",
      "filetype": "png"
    },
    {
      "id": 143,
      "title": "First Person Holding Shield",
      "credit": "",
      "filetype": "png"
    },
    {
      "id": 144,
      "title": "First Person Holding Stone Pickaxe",
      "credit": "",
      "filetype": "png"
    },
    {
      "id": 145,
      "title": "First Person Holding Stone Sword",
      "credit": "",
      "filetype": "png"
    },
    {
      "id": 146,
      "title": "First Person Holding Totem Of Undying.png",
      "credit": "",
      "filetype": "png"
    },
    {
      "id": 147,
      "title": "First Person Holding Water Bucket",
      "credit": "",
      "filetype": "png"
    },
    {
      "id": 148,
      "title": "First Person Holding Wooden Pickaxe",
      "credit": "",
      "filetype": "png"
    },
    {
      "id": 149,
      "title": "First Person Holding Wooden Sword",
      "credit": "",
      "filetype": "png"
    },
    {
      "id": 150,
      "title": "First Person Swinging Diamond Sword.png",
      "credit": "",
      "filetype": "png"
    },
    {
      "id": 151,
      "title": "Gwr Logo",
      "credit": "",
      "filetype": "png"
    },
    {
      "id": 152,
      "title": "Hacker Esp Lines",
      "credit": "",
      "filetype": "png"
    },
    {
      "id": 153,
      "title": "Headless Guy Explaining 2",
      "credit": "",
      "filetype": "png"
    },
    {
      "id": 154,
      "title": "Headless Guy Explaining",
      "credit": "",
      "filetype": "png"
    },
    {
      "id": 155,
      "title": "Headless Guy Happy",
      "credit": "",
      "filetype": "png"
    },
    {
      "id": 156,
      "title": "Headless Guy Leaning Against Wall",
      "credit": "",
      "filetype": "png"
    },
    {
      "id": 157,
      "title": "Headless Guy Pointing At You",
      "credit": "",
      "filetype": "png"
    },
    {
      "id": 158,
      "title": "Headless Guy Showing Something",
      "credit": "",
      "filetype": "png"
    },
    {
      "id": 159,
      "title": "Headless Guy Staring",
      "credit": "",
      "filetype": "png"
    },
    {
      "id": 160,
      "title": "Headless Guy Thumbs Up 2",
      "credit": "",
      "filetype": "png"
    },
    {
      "id": 161,
      "title": "Headless Guy Thumbs Up",
      "credit": "",
      "filetype": "png"
    },
    {
      "id": 162,
      "title": "Headless Guy Waving Saying Hi",
      "credit": "",
      "filetype": "png"
    },
    {
      "id": 163,
      "title": "Headless Guy With Computer",
      "credit": "",
      "filetype": "png"
    },
    {
      "id": 164,
      "title": "Heart Potion Hit Bubble Particles",
      "credit": "",
      "filetype": "png"
    },
    {
      "id": 165,
      "title": "Hit Particles",
      "credit": "",
      "filetype": "png"
    },
    {
      "id": 166,
      "title": "Hypixel Logo",
      "credit": "",
      "filetype": "png"
    },
    {
      "id": 167,
      "title": "Line Seperation Duel",
      "credit": "",
      "filetype": "png"
    },
    {
      "id": 168,
      "title": "Live Stream Button",
      "credit": "",
      "filetype": "png"
    },
    {
      "id": 169,
      "title": "Lunar Client Logo",
      "credit": "",
      "filetype": "png"
    },
    {
      "id": 170,
      "title": "Minecraft Logo",
      "credit": "",
      "filetype": "png"
    },
    {
      "id": 171,
      "title": "Minecraft You Died Death Overlay",
      "credit": "",
      "filetype": "png"
    },
    {
      "id": 172,
      "title": "Minemen Club Mmc Logo",
      "credit": "",
      "filetype": "png"
    },
    {
      "id": 173,
      "title": "Money Cash",
      "credit": "",
      "filetype": "png"
    },
    {
      "id": 174,
      "title": "Netherite Sword Holding",
      "credit": "",
      "filetype": "png"
    },
    {
      "id": 175,
      "title": "Obs Logo",
      "credit": "",
      "filetype": "png"
    },
    {
      "id": 176,
      "title": "Player Shadow",
      "credit": "",
      "filetype": "png"
    },
    {
      "id": 177,
      "title": "Questionmark",
      "credit": "",
      "filetype": "png"
    },
    {
      "id": 178,
      "title": "Red Button Without Text",
      "credit": "",
      "filetype": "png"
    },
    {
      "id": 179,
      "title": "Sky 1",
      "credit": "",
      "filetype": "jpg"
    },
    {
      "id": 180,
      "title": "Sky 1",
      "credit": "",
      "filetype": "png"
    },
    {
      "id": 181,
      "title": "Sky 10",
      "credit": "",
      "filetype": "png"
    },
    {
      "id": 182,
      "title": "Sky 11",
      "credit": "",
      "filetype": "png"
    },
    {
      "id": 183,
      "title": "Sky 12",
      "credit": "",
      "filetype": "png"
    },
    {
      "id": 184,
      "title": "Sky 13",
      "credit": "",
      "filetype": "png"
    },
    {
      "id": 185,
      "title": "Sky 14",
      "credit": "",
      "filetype": "png"
    },
    {
      "id": 186,
      "title": "Sky 15",
      "credit": "",
      "filetype": "png"
    },
    {
      "id": 187,
      "title": "Sky 16",
      "credit": "",
      "filetype": "png"
    },
    {
      "id": 188,
      "title": "Sky 2",
      "credit": "",
      "filetype": "jpg"
    },
    {
      "id": 189,
      "title": "Sky 2",
      "credit": "",
      "filetype": "png"
    },
    {
      "id": 190,
      "title": "Sky 3",
      "credit": "",
      "filetype": "png"
    },
    {
      "id": 191,
      "title": "Sky 4",
      "credit": "",
      "filetype": "png"
    },
    {
      "id": 192,
      "title": "Sky 5",
      "credit": "",
      "filetype": "png"
    },
    {
      "id": 193,
      "title": "Sky 6",
      "credit": "",
      "filetype": "png"
    },
    {
      "id": 194,
      "title": "Sky 7",
      "credit": "",
      "filetype": "png"
    },
    {
      "id": 195,
      "title": "Sky 8",
      "credit": "",
      "filetype": "png"
    },
    {
      "id": 196,
      "title": "Sky 9",
      "credit": "",
      "filetype": "png"
    },
    {
      "id": 197,
      "title": "Speedlines 2",
      "credit": "",
      "filetype": "png"
    },
    {
      "id": 198,
      "title": "Speedlines 3",
      "credit": "",
      "filetype": "png"
    },
    {
      "id": 199,
      "title": "Speedlines 4",
      "credit": "",
      "filetype": "png"
    },
    {
      "id": 200,
      "title": "Speedlines",
      "credit": "",
      "filetype": "png"
    },
    {
      "id": 201,
      "title": "Star",
      "credit": "",
      "filetype": "png"
    },
    {
      "id": 202,
      "title": "Sunburst",
      "credit": "",
      "filetype": "png"
    },
    {
      "id": 203,
      "title": "Swinging Hand",
      "credit": "",
      "filetype": "png"
    },
    {
      "id": 204,
      "title": "Tiktok Logo",
      "credit": "",
      "filetype": "png"
    },
    {
      "id": 205,
      "title": "Totem Pop Particles",
      "credit": "",
      "filetype": "png"
    },
    {
      "id": 206,
      "title": "Trophy",
      "credit": "",
      "filetype": "png"
    },
    {
      "id": 207,
      "title": "Twitch Logo",
      "credit": "",
      "filetype": "png"
    },
    {
      "id": 208,
      "title": "Vignette",
      "credit": "",
      "filetype": "png"
    },
    {
      "id": 209,
      "title": "X Twitter Logo",
      "credit": "",
      "filetype": "png"
    },
    {
      "id": 210,
      "title": "Youtube Logo 2",
      "credit": "",
      "filetype": "png"
    },
    {
      "id": 211,
      "title": "Youtube Logo",
      "credit": "",
      "filetype": "png"
    }
  ],
  "music": [
    {
      "id": 212,
      "title": "A Shattered Illusion",
      "credit": "",
      "filetype": "mp3"
    },
    {
      "id": 213,
      "title": "Ace - Verdant Green Swans",
      "credit": "",
      "filetype": "mp3"
    },
    {
      "id": 214,
      "title": "Action Suspense 2",
      "credit": "",
      "filetype": "mp3"
    },
    {
      "id": 215,
      "title": "Action Suspense",
      "credit": "",
      "filetype": "mp3"
    },
    {
      "id": 216,
      "title": "Adventurous",
      "credit": "",
      "filetype": "mp3"
    },
    {
      "id": 217,
      "title": "Anthony Vega - Johnny Vespa",
      "credit": "",
      "filetype": "mp3"
    },
    {
      "id": 218,
      "title": "Apassionato Orchestral Dramatic Music",
      "credit": "",
      "filetype": "mp3"
    },
    {
      "id": 219,
      "title": "At The Speed Of Light",
      "credit": "",
      "filetype": "mp3"
    },
    {
      "id": 220,
      "title": "Azali X Arcerion - Zephaniah",
      "credit": "",
      "filetype": "mp3"
    },
    {
      "id": 221,
      "title": "Background Music",
      "credit": "",
      "filetype": "mp3"
    },
    {
      "id": 222,
      "title": "Battle Against An Empire",
      "credit": "",
      "filetype": "mp3"
    },
    {
      "id": 223,
      "title": "Battle Of Birds And Pigs",
      "credit": "",
      "filetype": "mp3"
    },
    {
      "id": 224,
      "title": "Black Mass",
      "credit": "",
      "filetype": "mp3"
    },
    {
      "id": 225,
      "title": "Blizzard Peaks - Sonic Rush Adventure",
      "credit": "",
      "filetype": "mp3"
    },
    {
      "id": 226,
      "title": "Break Free",
      "credit": "",
      "filetype": "mp3"
    },
    {
      "id": 227,
      "title": "Camellia - The World Revolving (camellia Remix)",
      "credit": "",
      "filetype": "mp3"
    },
    {
      "id": 228,
      "title": "Chaos Construct (by Azali)",
      "credit": "",
      "filetype": "mp3"
    },
    {
      "id": 229,
      "title": "Chased By Fate",
      "credit": "",
      "filetype": "mp3"
    },
    {
      "id": 230,
      "title": "Cjbeards - Fire And Thunder",
      "credit": "",
      "filetype": "mp3"
    },
    {
      "id": 231,
      "title": "Corneria",
      "credit": "",
      "filetype": "mp3"
    },
    {
      "id": 232,
      "title": "Days Pass The Art Of Loneliness",
      "credit": "",
      "filetype": "mp3"
    },
    {
      "id": 233,
      "title": "Deep In The Forest",
      "credit": "",
      "filetype": "mp3"
    },
    {
      "id": 234,
      "title": "Deer Immaterial Anbr Adrian Berenguer",
      "credit": "",
      "filetype": "mp3"
    },
    {
      "id": 235,
      "title": "Dragon Castle",
      "credit": "_makai symphony - dragon castle_ is under a creative commons (by-nc 3.0) license_ @makai-symphony   music powered by breakingcopyright_    \u2022 \ud83d\udd25 epic battle music ",
      "filetype": "mp3"
    },
    {
      "id": 236,
      "title": "Dramatic Violin",
      "credit": "",
      "filetype": "mp3"
    },
    {
      "id": 237,
      "title": "End Of A Long Journey",
      "credit": "",
      "filetype": "mp3"
    },
    {
      "id": 238,
      "title": "Happy Energetic Boogie Fun",
      "credit": "",
      "filetype": "mp3"
    },
    {
      "id": 239,
      "title": "Haunted Mansion",
      "credit": "",
      "filetype": "mp3"
    },
    {
      "id": 240,
      "title": "Iby - Dj B-duke",
      "credit": "",
      "filetype": "mp3"
    },
    {
      "id": 241,
      "title": "Infraction - Atlas",
      "credit": "",
      "filetype": "mp3"
    },
    {
      "id": 242,
      "title": "Journey Through The Woods",
      "credit": "",
      "filetype": "mp3"
    },
    {
      "id": 243,
      "title": "King Pig And His Manic Minions",
      "credit": "",
      "filetype": "mp3"
    },
    {
      "id": 244,
      "title": "Move Like This - Jules Gaia",
      "credit": "",
      "filetype": "mp3"
    },
    {
      "id": 245,
      "title": "New World",
      "credit": "",
      "filetype": "mp3"
    },
    {
      "id": 246,
      "title": "Oh What A Whirl - Jules Gaia",
      "credit": "",
      "filetype": "mp3"
    },
    {
      "id": 247,
      "title": "Popcorn Castle",
      "credit": "",
      "filetype": "mp3"
    },
    {
      "id": 248,
      "title": "Qbedwars Music",
      "credit": "",
      "filetype": "mp3"
    },
    {
      "id": 249,
      "title": "Quo Vadis",
      "credit": "",
      "filetype": "mp3"
    },
    {
      "id": 250,
      "title": "Run Fast Instrumental",
      "credit": "",
      "filetype": "mp3"
    },
    {
      "id": 251,
      "title": "Shake Down - Jules Gaia",
      "credit": "",
      "filetype": "mp3"
    },
    {
      "id": 252,
      "title": "Sparkling Stars",
      "credit": "",
      "filetype": "mp3"
    },
    {
      "id": 253,
      "title": "Totally Not A Rickroll",
      "credit": "",
      "filetype": "mp3"
    },
    {
      "id": 254,
      "title": "Undertale Ost Spear Of Justice",
      "credit": "",
      "filetype": "mp3"
    },
    {
      "id": 255,
      "title": "Unstoppable Force",
      "credit": "",
      "filetype": "mp3"
    },
    {
      "id": 256,
      "title": "Welcome To Chaos - Ross Bugden",
      "credit": "",
      "filetype": "mp3"
    },
    {
      "id": 257,
      "title": "Windmill Isle - Day",
      "credit": "",
      "filetype": "mp3"
    }
  ],
  "presets": [
    {
      "id": 258,
      "title": "Animated Turbulence Displace",
      "credit": "",
      "filetype": "ffx",
      "subcategory": "adobe"
    },
    {
      "id": 259,
      "title": "Animated Turbulence Displacement",
      "credit": "",
      "filetype": "ffx",
      "subcategory": "adobe"
    },
    {
      "id": 260,
      "title": "Blur And Exposure",
      "credit": "",
      "filetype": "ffx",
      "subcategory": "adobe"
    },
    {
      "id": 261,
      "title": "Bounce Effect",
      "credit": "",
      "filetype": "txt",
      "subcategory": "adobe"
    },
    {
      "id": 262,
      "title": "Chain Locked Logo Smp",
      "credit": "",
      "filetype": "prproj",
      "subcategory": "adobe"
    },
    {
      "id": 263,
      "title": "Drop Shadow+",
      "credit": "",
      "filetype": "ffx",
      "subcategory": "adobe"
    },
    {
      "id": 264,
      "title": "Drop Shadow",
      "credit": "",
      "filetype": "ffx",
      "subcategory": "adobe"
    },
    {
      "id": 265,
      "title": "Grain",
      "credit": "",
      "filetype": "ffx",
      "subcategory": "adobe"
    },
    {
      "id": 266,
      "title": "Grid Scanlines",
      "credit": "",
      "filetype": "ffx",
      "subcategory": "adobe"
    },
    {
      "id": 267,
      "title": "Light Sweep",
      "credit": "",
      "filetype": "ffx",
      "subcategory": "adobe"
    },
    {
      "id": 268,
      "title": "Like And Subscribe",
      "credit": "Henry DG",
      "filetype": "mogrt",
      "subcategory": "adobe"
    },
    {
      "id": 269,
      "title": "Noise Preset",
      "credit": "",
      "filetype": "ffx",
      "subcategory": "adobe"
    },
    {
      "id": 270,
      "title": "Number Counter",
      "credit": "",
      "filetype": "ffx",
      "subcategory": "adobe"
    },
    {
      "id": 271,
      "title": "Posterize",
      "credit": "",
      "filetype": "ffx",
      "subcategory": "adobe"
    },
    {
      "id": 272,
      "title": "Repe And Glow",
      "credit": "",
      "filetype": "ffx",
      "subcategory": "adobe"
    },
    {
      "id": 273,
      "title": "Repe",
      "credit": "",
      "filetype": "ffx",
      "subcategory": "adobe"
    },
    {
      "id": 274,
      "title": "Rimlight And Glow",
      "credit": "",
      "filetype": "ffx",
      "subcategory": "adobe"
    },
    {
      "id": 275,
      "title": "Rimlight Repe Glow",
      "credit": "",
      "filetype": "ffx",
      "subcategory": "adobe"
    },
    {
      "id": 276,
      "title": "Round Corners",
      "credit": "",
      "filetype": "ffx",
      "subcategory": "adobe"
    },
    {
      "id": 277,
      "title": "Slide Left Text",
      "credit": "",
      "filetype": "ffx",
      "subcategory": "adobe"
    },
    {
      "id": 278,
      "title": "Slide Up Text",
      "credit": "",
      "filetype": "ffx",
      "subcategory": "adobe"
    },
    {
      "id": 279,
      "title": "Trim Paths",
      "credit": "",
      "filetype": "ffx",
      "subcategory": "adobe"
    },
    {
      "id": 280,
      "title": "Wiggle Etc",
      "credit": "",
      "filetype": "ffx",
      "subcategory": "adobe"
    },
    {
      "id": 281,
      "title": "Apie Flicker Buildup",
      "credit": "",
      "filetype": "setting",
      "subcategory": "davinci"
    },
    {
      "id": 282,
      "title": "Displacementmap",
      "credit": "",
      "filetype": "setting",
      "subcategory": "davinci"
    },
    {
      "id": 283,
      "title": "Distort",
      "credit": "",
      "filetype": "setting",
      "subcategory": "davinci"
    },
    {
      "id": 284,
      "title": "Gradientmap",
      "credit": "",
      "filetype": "setting",
      "subcategory": "davinci"
    },
    {
      "id": 285,
      "title": "Guidelines",
      "credit": "",
      "filetype": "setting",
      "subcategory": "davinci"
    },
    {
      "id": 286,
      "title": "Impact",
      "credit": "",
      "filetype": "setting",
      "subcategory": "davinci"
    },
    {
      "id": 287,
      "title": "Millovhs",
      "credit": "",
      "filetype": "setting",
      "subcategory": "davinci"
    },
    {
      "id": 288,
      "title": "Multimerge",
      "credit": "",
      "filetype": "setting",
      "subcategory": "davinci"
    },
    {
      "id": 289,
      "title": "Ngongrid",
      "credit": "",
      "filetype": "setting",
      "subcategory": "davinci"
    },
    {
      "id": 290,
      "title": "Opacity Masking Tool",
      "credit": "",
      "filetype": "setting",
      "subcategory": "davinci"
    },
    {
      "id": 291,
      "title": "Particle",
      "credit": "",
      "filetype": "setting",
      "subcategory": "davinci"
    },
    {
      "id": 292,
      "title": "Player Joined Text Animation",
      "credit": "",
      "filetype": "comp",
      "subcategory": "davinci"
    },
    {
      "id": 293,
      "title": "Progress Bar",
      "credit": "",
      "filetype": "drp",
      "subcategory": "davinci"
    },
    {
      "id": 294,
      "title": "Rainbow Gradient",
      "credit": "",
      "filetype": "setting",
      "subcategory": "davinci"
    },
    {
      "id": 295,
      "title": "Refraction Mirrored",
      "credit": "",
      "filetype": "setting",
      "subcategory": "davinci"
    },
    {
      "id": 296,
      "title": "Refraction",
      "credit": "",
      "filetype": "setting",
      "subcategory": "davinci"
    },
    {
      "id": 297,
      "title": "Rgb Split Directional",
      "credit": "",
      "filetype": "setting",
      "subcategory": "davinci"
    },
    {
      "id": 298,
      "title": "Rgb Split Through Center",
      "credit": "",
      "filetype": "setting",
      "subcategory": "davinci"
    },
    {
      "id": 299,
      "title": "Sexy Sxpphaa Beatshake",
      "credit": "",
      "filetype": "setting",
      "subcategory": "davinci"
    },
    {
      "id": 300,
      "title": "Tempest Presets",
      "credit": "",
      "filetype": "drp",
      "subcategory": "davinci"
    },
    {
      "id": 301,
      "title": "Transition Down Left",
      "credit": "",
      "filetype": "setting",
      "subcategory": "davinci"
    },
    {
      "id": 302,
      "title": "Transition Down Right",
      "credit": "",
      "filetype": "setting",
      "subcategory": "davinci"
    },
    {
      "id": 303,
      "title": "Transition Down",
      "credit": "",
      "filetype": "setting",
      "subcategory": "davinci"
    },
    {
      "id": 304,
      "title": "Transition Left",
      "credit": "",
      "filetype": "setting",
      "subcategory": "davinci"
    },
    {
      "id": 305,
      "title": "Transition Right",
      "credit": "",
      "filetype": "setting",
      "subcategory": "davinci"
    },
    {
      "id": 306,
      "title": "Transition Spin Clockwise",
      "credit": "",
      "filetype": "setting",
      "subcategory": "davinci"
    },
    {
      "id": 307,
      "title": "Transition Spin Counterclockwise",
      "credit": "",
      "filetype": "setting",
      "subcategory": "davinci"
    },
    {
      "id": 308,
      "title": "Transition Top Left",
      "credit": "",
      "filetype": "setting",
      "subcategory": "davinci"
    },
    {
      "id": 309,
      "title": "Transition Top Right",
      "credit": "",
      "filetype": "setting",
      "subcategory": "davinci"
    },
    {
      "id": 310,
      "title": "Transition Up",
      "credit": "",
      "filetype": "setting",
      "subcategory": "davinci"
    },
    {
      "id": 311,
      "title": "Velocity",
      "credit": "",
      "filetype": "setting",
      "subcategory": "davinci"
    },
    {
      "id": 312,
      "title": "Wipe Transition",
      "credit": "",
      "filetype": "drp",
      "subcategory": "davinci"
    }
  ],
  "sfx": [
    {
      "id": 313,
      "title": "Air Leak",
      "credit": "",
      "filetype": "wav"
    },
    {
      "id": 314,
      "title": "Airhorn",
      "credit": "",
      "filetype": "wav"
    },
    {
      "id": 315,
      "title": "Ambient Hits",
      "credit": "",
      "filetype": "mp3"
    },
    {
      "id": 316,
      "title": "Anime Wow",
      "credit": "",
      "filetype": "mp3"
    },
    {
      "id": 317,
      "title": "Anvil Hit",
      "credit": "",
      "filetype": "wav"
    },
    {
      "id": 318,
      "title": "Applause 2",
      "credit": "",
      "filetype": "wav"
    },
    {
      "id": 319,
      "title": "Applause",
      "credit": "",
      "filetype": "wav"
    },
    {
      "id": 320,
      "title": "Apple Notification",
      "credit": "",
      "filetype": "wav"
    },
    {
      "id": 321,
      "title": "Augggh",
      "credit": "",
      "filetype": "mp3"
    },
    {
      "id": 322,
      "title": "Awww Cute",
      "credit": "",
      "filetype": "mp3"
    },
    {
      "id": 323,
      "title": "Baby Cry",
      "credit": "",
      "filetype": "wav"
    },
    {
      "id": 324,
      "title": "Baby",
      "credit": "",
      "filetype": "wav"
    },
    {
      "id": 325,
      "title": "Balloon Pop",
      "credit": "",
      "filetype": "wav"
    },
    {
      "id": 326,
      "title": "Baseball Hit 1",
      "credit": "",
      "filetype": "wav"
    },
    {
      "id": 327,
      "title": "Baseball Hit 2",
      "credit": "",
      "filetype": "wav"
    },
    {
      "id": 328,
      "title": "Baseball Hit Cheer 1",
      "credit": "",
      "filetype": "wav"
    },
    {
      "id": 329,
      "title": "Baseball Hit Cheer 2",
      "credit": "",
      "filetype": "wav"
    },
    {
      "id": 330,
      "title": "Baseball Metal Bat",
      "credit": "",
      "filetype": "wav"
    },
    {
      "id": 331,
      "title": "Baseball Wooden Bat",
      "credit": "",
      "filetype": "wav"
    },
    {
      "id": 332,
      "title": "Basket Ball Bounce",
      "credit": "",
      "filetype": "wav"
    },
    {
      "id": 333,
      "title": "Basketball Backboard",
      "credit": "",
      "filetype": "wav"
    },
    {
      "id": 334,
      "title": "Basketball Dribble",
      "credit": "",
      "filetype": "wav"
    },
    {
      "id": 335,
      "title": "Basketball Swish",
      "credit": "",
      "filetype": "wav"
    },
    {
      "id": 336,
      "title": "Bassy Swoosh",
      "credit": "",
      "filetype": "wav"
    },
    {
      "id": 337,
      "title": "Batman Transition",
      "credit": "",
      "filetype": "wav"
    },
    {
      "id": 338,
      "title": "Bell Drum Dull Church",
      "credit": "",
      "filetype": "wav"
    },
    {
      "id": 339,
      "title": "Bing",
      "credit": "",
      "filetype": "wav"
    },
    {
      "id": 340,
      "title": "Bird Cardinal",
      "credit": "",
      "filetype": "wav"
    },
    {
      "id": 341,
      "title": "Bird Chirp 1",
      "credit": "",
      "filetype": "wav"
    },
    {
      "id": 342,
      "title": "Bird Chirp 2",
      "credit": "",
      "filetype": "wav"
    },
    {
      "id": 343,
      "title": "Bird Chirp 3",
      "credit": "",
      "filetype": "wav"
    },
    {
      "id": 344,
      "title": "Blech Burp",
      "credit": "",
      "filetype": "wav"
    },
    {
      "id": 345,
      "title": "Blunt Impact Splatter Death",
      "credit": "",
      "filetype": "wav"
    },
    {
      "id": 346,
      "title": "Boiling Crash Boom",
      "credit": "",
      "filetype": "mp3"
    },
    {
      "id": 347,
      "title": "Button Click",
      "credit": "",
      "filetype": "wav"
    },
    {
      "id": 348,
      "title": "Bye Have A Great Day",
      "credit": "",
      "filetype": "mp3"
    },
    {
      "id": 349,
      "title": "Camera Shutter 1",
      "credit": "",
      "filetype": "wav"
    },
    {
      "id": 350,
      "title": "Camera Shutter 10",
      "credit": "",
      "filetype": "mp3"
    },
    {
      "id": 351,
      "title": "Camera Shutter 11",
      "credit": "",
      "filetype": "mp3"
    },
    {
      "id": 352,
      "title": "Camera Shutter 12",
      "credit": "",
      "filetype": "wav"
    },
    {
      "id": 353,
      "title": "Camera Shutter 13",
      "credit": "",
      "filetype": "wav"
    },
    {
      "id": 354,
      "title": "Camera Shutter 14",
      "credit": "",
      "filetype": "wav"
    },
    {
      "id": 355,
      "title": "Camera Shutter 15",
      "credit": "",
      "filetype": "wav"
    },
    {
      "id": 356,
      "title": "Camera Shutter 16",
      "credit": "",
      "filetype": "wav"
    },
    {
      "id": 357,
      "title": "Camera Shutter 2",
      "credit": "",
      "filetype": "mp3"
    },
    {
      "id": 358,
      "title": "Camera Shutter 3",
      "credit": "",
      "filetype": "mp3"
    },
    {
      "id": 359,
      "title": "Camera Shutter 4",
      "credit": "",
      "filetype": "mp3"
    },
    {
      "id": 360,
      "title": "Camera Shutter 5",
      "credit": "",
      "filetype": "mp3"
    },
    {
      "id": 361,
      "title": "Camera Shutter 6",
      "credit": "",
      "filetype": "wav"
    },
    {
      "id": 362,
      "title": "Camera Shutter 7",
      "credit": "",
      "filetype": "wav"
    },
    {
      "id": 363,
      "title": "Camera Shutter 8",
      "credit": "",
      "filetype": "wav"
    },
    {
      "id": 364,
      "title": "Camera Shutter 9",
      "credit": "",
      "filetype": "wav"
    },
    {
      "id": 365,
      "title": "Cartoon Sound Effects Pop",
      "credit": "",
      "filetype": "wav"
    },
    {
      "id": 366,
      "title": "Cash Register 1",
      "credit": "",
      "filetype": "wav"
    },
    {
      "id": 367,
      "title": "Cash Register 2",
      "credit": "",
      "filetype": "wav"
    },
    {
      "id": 368,
      "title": "Cell Phone Ringing",
      "credit": "",
      "filetype": "mp3"
    },
    {
      "id": 369,
      "title": "Check 1",
      "credit": "",
      "filetype": "mp3"
    },
    {
      "id": 370,
      "title": "Check 2",
      "credit": "",
      "filetype": "wav"
    },
    {
      "id": 371,
      "title": "Check 3",
      "credit": "",
      "filetype": "mp3"
    },
    {
      "id": 372,
      "title": "Check 4",
      "credit": "",
      "filetype": "mp3"
    },
    {
      "id": 373,
      "title": "Check 5",
      "credit": "",
      "filetype": "mp3"
    },
    {
      "id": 374,
      "title": "Cinem Wave Swoosh",
      "credit": "",
      "filetype": "wav"
    },
    {
      "id": 375,
      "title": "Cinematic Bass Boom",
      "credit": "",
      "filetype": "mp3"
    },
    {
      "id": 376,
      "title": "Cinematic Boom Hollow",
      "credit": "",
      "filetype": "wav"
    },
    {
      "id": 377,
      "title": "Coins Money",
      "credit": "",
      "filetype": "wav"
    },
    {
      "id": 378,
      "title": "Dafuq Wazzat",
      "credit": "",
      "filetype": "mp3"
    },
    {
      "id": 379,
      "title": "Dang It",
      "credit": "",
      "filetype": "wav"
    },
    {
      "id": 380,
      "title": "Deep Woosh",
      "credit": "",
      "filetype": "wav"
    },
    {
      "id": 381,
      "title": "Denied Sound",
      "credit": "",
      "filetype": "mp3"
    },
    {
      "id": 382,
      "title": "Digital Whoosh",
      "credit": "",
      "filetype": "wav"
    },
    {
      "id": 383,
      "title": "Discord Airhorn",
      "credit": "",
      "filetype": "wav"
    },
    {
      "id": 384,
      "title": "Discord Leave",
      "credit": "",
      "filetype": "mp3"
    },
    {
      "id": 385,
      "title": "Dj Record Scratch",
      "credit": "",
      "filetype": "wav"
    },
    {
      "id": 386,
      "title": "Dramatic Event V1",
      "credit": "",
      "filetype": "wav"
    },
    {
      "id": 387,
      "title": "Dramatic Event V2",
      "credit": "",
      "filetype": "wav"
    },
    {
      "id": 388,
      "title": "Dramatic Event V3",
      "credit": "",
      "filetype": "wav"
    },
    {
      "id": 389,
      "title": "Echo Dull Swish",
      "credit": "",
      "filetype": "wav"
    },
    {
      "id": 390,
      "title": "Echo Swoosh",
      "credit": "",
      "filetype": "wav"
    },
    {
      "id": 391,
      "title": "Eelectronic Woosh",
      "credit": "",
      "filetype": "wav"
    },
    {
      "id": 392,
      "title": "Embers Fire",
      "credit": "",
      "filetype": "mp3"
    },
    {
      "id": 393,
      "title": "Error",
      "credit": "",
      "filetype": "mp3"
    },
    {
      "id": 394,
      "title": "Evil Laugh",
      "credit": "",
      "filetype": "mp3"
    },
    {
      "id": 395,
      "title": "Explosion",
      "credit": "",
      "filetype": "wav"
    },
    {
      "id": 396,
      "title": "Fall To Death",
      "credit": "",
      "filetype": "wav"
    },
    {
      "id": 397,
      "title": "Fast Suspense Transition",
      "credit": "",
      "filetype": "mp3"
    },
    {
      "id": 398,
      "title": "Fast Woosh 1",
      "credit": "",
      "filetype": "mp3"
    },
    {
      "id": 399,
      "title": "Fast Woosh 2",
      "credit": "",
      "filetype": "mp3"
    },
    {
      "id": 400,
      "title": "Fast Woosh 3",
      "credit": "",
      "filetype": "mp3"
    },
    {
      "id": 401,
      "title": "Fast Woosh 4",
      "credit": "",
      "filetype": "mp3"
    },
    {
      "id": 402,
      "title": "Fast Woosh 5",
      "credit": "",
      "filetype": "mp3"
    },
    {
      "id": 403,
      "title": "Fat Juicy Fart",
      "credit": "",
      "filetype": "mp3"
    },
    {
      "id": 404,
      "title": "Film Shutter",
      "credit": "",
      "filetype": "wav"
    },
    {
      "id": 405,
      "title": "Flashback",
      "credit": "",
      "filetype": "wav"
    },
    {
      "id": 406,
      "title": "Footsteps",
      "credit": "",
      "filetype": "mp3"
    },
    {
      "id": 407,
      "title": "Game Achievement Reached",
      "credit": "",
      "filetype": "wav"
    },
    {
      "id": 408,
      "title": "Game Counter Or Digital Data Readout Sound Pack",
      "credit": "",
      "filetype": "mp3"
    },
    {
      "id": 409,
      "title": "Game Item Pickup",
      "credit": "",
      "filetype": "mp3"
    },
    {
      "id": 410,
      "title": "Gaming Mouse Button Click",
      "credit": "",
      "filetype": "mp3"
    },
    {
      "id": 411,
      "title": "Handwriting 1",
      "credit": "",
      "filetype": "mp3"
    },
    {
      "id": 412,
      "title": "Handwriting 2",
      "credit": "",
      "filetype": "mp3"
    },
    {
      "id": 413,
      "title": "Heavy Slow Woosh",
      "credit": "",
      "filetype": "mp3"
    },
    {
      "id": 414,
      "title": "Iphone Ringtone",
      "credit": "",
      "filetype": "mp3"
    },
    {
      "id": 415,
      "title": "Iphone Text Message Receive",
      "credit": "",
      "filetype": "wav"
    },
    {
      "id": 416,
      "title": "Keyboard Typing",
      "credit": "",
      "filetype": "wav"
    },
    {
      "id": 417,
      "title": "Kids Yay",
      "credit": "",
      "filetype": "mp3"
    },
    {
      "id": 418,
      "title": "Lightsaber",
      "credit": "",
      "filetype": "mp3"
    },
    {
      "id": 419,
      "title": "Manual Page Turn",
      "credit": "",
      "filetype": "mp3"
    },
    {
      "id": 420,
      "title": "Paddle Ball Hit 1",
      "credit": "",
      "filetype": "wav"
    },
    {
      "id": 421,
      "title": "Paper Crumbling",
      "credit": "",
      "filetype": "wav"
    },
    {
      "id": 422,
      "title": "Pencil Rubing",
      "credit": "",
      "filetype": "mp3"
    },
    {
      "id": 423,
      "title": "Pop 1",
      "credit": "",
      "filetype": "mp3"
    },
    {
      "id": 424,
      "title": "Pop 2",
      "credit": "",
      "filetype": "mp3"
    },
    {
      "id": 425,
      "title": "Power Down 03, Slow",
      "credit": "",
      "filetype": "wav"
    },
    {
      "id": 426,
      "title": "Punch",
      "credit": "",
      "filetype": "wav"
    },
    {
      "id": 427,
      "title": "Punch2",
      "credit": "",
      "filetype": "wav"
    },
    {
      "id": 428,
      "title": "Rain 2",
      "credit": "",
      "filetype": "wav"
    },
    {
      "id": 429,
      "title": "Rain",
      "credit": "",
      "filetype": "wav"
    },
    {
      "id": 430,
      "title": "Record Scratch",
      "credit": "",
      "filetype": "wav"
    },
    {
      "id": 431,
      "title": "Riser 2",
      "credit": "",
      "filetype": "wav"
    },
    {
      "id": 432,
      "title": "Riser 3",
      "credit": "",
      "filetype": "wav"
    },
    {
      "id": 433,
      "title": "Riser 4",
      "credit": "",
      "filetype": "wav"
    },
    {
      "id": 434,
      "title": "Riser 5",
      "credit": "",
      "filetype": "mp3"
    },
    {
      "id": 435,
      "title": "Riser 6",
      "credit": "",
      "filetype": "wav"
    },
    {
      "id": 436,
      "title": "Riser",
      "credit": "",
      "filetype": "mp3"
    },
    {
      "id": 437,
      "title": "Rocky Explosion",
      "credit": "",
      "filetype": "wav"
    },
    {
      "id": 438,
      "title": "Satisfying Click Tick Check",
      "credit": "",
      "filetype": "wav"
    },
    {
      "id": 439,
      "title": "Shiny Ding Sound Effect",
      "credit": "",
      "filetype": "mp3"
    },
    {
      "id": 440,
      "title": "Slice Woosh",
      "credit": "",
      "filetype": "wav"
    },
    {
      "id": 441,
      "title": "Smash Break Throw",
      "credit": "",
      "filetype": "wav"
    },
    {
      "id": 442,
      "title": "Smooth Woosh",
      "credit": "",
      "filetype": "wav"
    },
    {
      "id": 443,
      "title": "Splat Sound Effect",
      "credit": "",
      "filetype": "mp3"
    },
    {
      "id": 444,
      "title": "Sudden Impact 2",
      "credit": "",
      "filetype": "wav"
    },
    {
      "id": 445,
      "title": "Sudden Impact 3",
      "credit": "",
      "filetype": "wav"
    },
    {
      "id": 446,
      "title": "Sudden Impact",
      "credit": "",
      "filetype": "wav"
    },
    {
      "id": 447,
      "title": "Surprise Motherfucker",
      "credit": "",
      "filetype": "wav"
    },
    {
      "id": 448,
      "title": "Swish Reverse Intervention",
      "credit": "zebo",
      "filetype": "mp3"
    },
    {
      "id": 449,
      "title": "Tearing Paper Apart",
      "credit": "",
      "filetype": "wav"
    },
    {
      "id": 450,
      "title": "Tv Noise 1",
      "credit": "",
      "filetype": "wav"
    },
    {
      "id": 451,
      "title": "Tv Noise 2",
      "credit": "",
      "filetype": "wav"
    },
    {
      "id": 452,
      "title": "Tv Noise 3",
      "credit": "",
      "filetype": "wav"
    },
    {
      "id": 453,
      "title": "Typewriter 2",
      "credit": "",
      "filetype": "wav"
    },
    {
      "id": 454,
      "title": "Ui Beep 1",
      "credit": "",
      "filetype": "wav"
    },
    {
      "id": 455,
      "title": "Ui Beep 2",
      "credit": "",
      "filetype": "mp3"
    },
    {
      "id": 456,
      "title": "Ui Beep 3",
      "credit": "",
      "filetype": "wav"
    },
    {
      "id": 457,
      "title": "Ui Beep 4",
      "credit": "",
      "filetype": "wav"
    },
    {
      "id": 458,
      "title": "Ui Beep 5",
      "credit": "",
      "filetype": "wav"
    },
    {
      "id": 459,
      "title": "Video Game Arpeggio",
      "credit": "",
      "filetype": "mp3"
    },
    {
      "id": 460,
      "title": "Water Drop",
      "credit": "",
      "filetype": "wav"
    },
    {
      "id": 461,
      "title": "Water, Wave, Surge, Cinematic 02",
      "credit": "",
      "filetype": "mp3"
    },
    {
      "id": 462,
      "title": "Whoosh 1",
      "credit": "",
      "filetype": "wav"
    },
    {
      "id": 463,
      "title": "Whoosh 2",
      "credit": "",
      "filetype": "wav"
    },
    {
      "id": 464,
      "title": "Whoosh 3",
      "credit": "",
      "filetype": "wav"
    },
    {
      "id": 465,
      "title": "Whoosh 4",
      "credit": "",
      "filetype": "wav"
    },
    {
      "id": 466,
      "title": "Whoosh 5",
      "credit": "",
      "filetype": "wav"
    },
    {
      "id": 467,
      "title": "Whoosh Deep Light 2",
      "credit": "",
      "filetype": "wav"
    },
    {
      "id": 468,
      "title": "Whoosh Deep Light",
      "credit": "",
      "filetype": "wav"
    },
    {
      "id": 469,
      "title": "Whoosh Deep Short",
      "credit": "",
      "filetype": "wav"
    },
    {
      "id": 470,
      "title": "Whoosh Deep",
      "credit": "",
      "filetype": "wav"
    },
    {
      "id": 471,
      "title": "Whoosh Fast",
      "credit": "",
      "filetype": "wav"
    },
    {
      "id": 472,
      "title": "Whoosh Fire 2",
      "credit": "",
      "filetype": "wav"
    },
    {
      "id": 473,
      "title": "Whoosh Fire",
      "credit": "",
      "filetype": "wav"
    },
    {
      "id": 474,
      "title": "Whoosh Light Long 1",
      "credit": "",
      "filetype": "wav"
    },
    {
      "id": 475,
      "title": "Whoosh Light Long 2",
      "credit": "",
      "filetype": "wav"
    },
    {
      "id": 476,
      "title": "Whoosh Light Short",
      "credit": "",
      "filetype": "wav"
    },
    {
      "id": 477,
      "title": "Whoosh Light",
      "credit": "",
      "filetype": "wav"
    },
    {
      "id": 478,
      "title": "Whoosh Main 2",
      "credit": "",
      "filetype": "wav"
    },
    {
      "id": 479,
      "title": "Whoosh Main",
      "credit": "",
      "filetype": "wav"
    },
    {
      "id": 480,
      "title": "Whoosh Reverbed",
      "credit": "",
      "filetype": "wav"
    },
    {
      "id": 481,
      "title": "Whoosh Short",
      "credit": "",
      "filetype": "wav"
    },
    {
      "id": 482,
      "title": "Youve Got Mail",
      "credit": "",
      "filetype": "wav"
    }
  ]
}